[
    {
        "impressions": "480",
        "account_id": "1154015138307321",
        "reach": "347",
        "spend": "11.54",
        "adset_id": "120215275579080172",
        "adset_name": "Geolocalizado 5km",
        "ad_id": "120215813660460172",
        "ad_name": "Odonto",
        "actions": [
            {
                "action_type": "page_engagement",
                "value": "63"
            },
            {
                "action_type": "post_engagement",
                "value": "63"
            },
            {
                "action_type": "video_view",
                "value": "61"
            },
            {
                "action_type": "link_click",
                "value": "2"
            }
        ],
        "date_start": "2025-03-15",
        "date_stop": "2025-03-15"
    },
    {
        "impressions": "4443",
        "account_id": "1154015138307321",
        "reach": "3867",
        "spend": "29.76",
        "adset_id": "120217426004670172",
        "adset_name": "Geolocalizado Nassau Parangaba",
        "ad_id": "120217426004690172",
        "ad_name": "Mês do consumidor",
        "actions": [
            {
                "action_type": "page_engagement",
                "value": "23"
            },
            {
                "action_type": "post_engagement",
                "value": "23"
            },
            {
                "action_type": "lead",
                "value": "4"
            },
            {
                "action_type": "onsite_conversion.lead_grouped",
                "value": "4"
            },
            {
                "action_type": "post_reaction",
                "value": "1"
            },
            {
                "action_type": "link_click",
                "value": "22"
            }
        ],
        "date_start": "2025-03-15",
        "date_stop": "2025-03-15"
    },
    {
        "impressions": "1541",
        "account_id": "1154015138307321",
        "reach": "1081",
        "spend": "17.59",
        "adset_id": "120215275579080172",
        "adset_name": "Geolocalizado 5km",
        "ad_id": "120217727664820172",
        "ad_name": "Nutrição",
        "actions": [
            {
                "action_type": "page_engagement",
                "value": "165"
            },
            {
                "action_type": "post_engagement",
                "value": "165"
            },
            {
                "action_type": "video_view",
                "value": "162"
            },
            {
                "action_type": "link_click",
                "value": "3"
            }
        ],
        "date_start": "2025-03-15",
        "date_stop": "2025-03-15"
    },
    {
        "impressions": "7771",
        "account_id": "1154015138307321",
        "reach": "5830",
        "spend": "46.25",
        "adset_id": "120217426004670172",
        "adset_name": "Geolocalizado Nassau Parangaba",
        "ad_id": "120217997650510172",
        "ad_name": "Mês do consumidor 2",
        "actions": [
            {
                "action_type": "page_engagement",
                "value": "30"
            },
            {
                "action_type": "post_engagement",
                "value": "30"
            },
            {
                "action_type": "lead",
                "value": "5"
            },
            {
                "action_type": "onsite_conversion.lead_grouped",
                "value": "5"
            },
            {
                "action_type": "link_click",
                "value": "30"
            }
        ],
        "date_start": "2025-03-15",
        "date_stop": "2025-03-15"
    }
]