[
    {
        "impressions": "8072",
        "account_id": "1213925972283556",
        "reach": "7942",
        "spend": "24.92",
        "adset_id": "120219761045980221",
        "adset_name": "00 | ADV+ | AUTO | 0703",
        "ad_id": "120219762028880221",
        "ad_name": "AD01 | \"8 Motivos para escolher Garanhuns | 0703",
        "actions": [
            {
                "action_type": "page_engagement",
                "value": "1019"
            },
            {
                "action_type": "post_engagement",
                "value": "1019"
            },
            {
                "action_type": "video_view",
                "value": "943"
            },
            {
                "action_type": "link_click",
                "value": "76"
            }
        ],
        "date_start": "2025-03-30",
        "date_stop": "2025-03-30"
    },
    {
        "impressions": "322",
        "account_id": "1213925972283556",
        "reach": "233",
        "spend": "3.04",
        "adset_id": "120220302929240221",
        "adset_name": "05 | ADV+ | PROMO_01 | 0104",
        "ad_id": "120220302929230221",
        "ad_name": "AD12 | \"Coordenadora Enfermagem\" | 2003 — Cópia",
        "actions": [
            {
                "action_type": "page_engagement",
                "value": "44"
            },
            {
                "action_type": "post_engagement",
                "value": "44"
            },
            {
                "action_type": "video_view",
                "value": "43"
            },
            {
                "action_type": "link_click",
                "value": "1"
            }
        ],
        "date_start": "2025-03-30",
        "date_stop": "2025-03-30"
    },
    {
        "impressions": "725",
        "account_id": "1213925972283556",
        "reach": "497",
        "spend": "9.36",
        "adset_id": "120220302929240221",
        "adset_name": "05 | ADV+ | PROMO_01 | 0104",
        "ad_id": "120220302929260221",
        "ad_name": "AD08 | \"Consumidor\" | 0503",
        "actions": [
            {
                "action_type": "page_engagement",
                "value": "1"
            },
            {
                "action_type": "post_engagement",
                "value": "1"
            },
            {
                "action_type": "link_click",
                "value": "1"
            }
        ],
        "date_start": "2025-03-30",
        "date_stop": "2025-03-30"
    },
    {
        "impressions": "158",
        "account_id": "1213925972283556",
        "reach": "131",
        "spend": "0.99",
        "adset_id": "120220302929240221",
        "adset_name": "05 | ADV+ | PROMO_01 | 0104",
        "ad_id": "120220302929280221",
        "ad_name": "AD10 | \"Coordenador MedVet\" | 2003 — Cópia",
        "actions": [
            {
                "action_type": "page_engagement",
                "value": "22"
            },
            {
                "action_type": "post_engagement",
                "value": "22"
            },
            {
                "action_type": "video_view",
                "value": "16"
            },
            {
                "action_type": "post_reaction",
                "value": "3"
            },
            {
                "action_type": "link_click",
                "value": "3"
            }
        ],
        "date_start": "2025-03-30",
        "date_stop": "2025-03-30"
    },
    {
        "impressions": "332",
        "account_id": "1213925972283556",
        "reach": "246",
        "spend": "3.62",
        "adset_id": "120220302929240221",
        "adset_name": "05 | ADV+ | PROMO_01 | 0104",
        "ad_id": "120220302929290221",
        "ad_name": "AD11 | \"Coordenadora Direito\" | 2003 — Cópia",
        "actions": [
            {
                "action_type": "page_engagement",
                "value": "68"
            },
            {
                "action_type": "post_engagement",
                "value": "68"
            },
            {
                "action_type": "video_view",
                "value": "64"
            },
            {
                "action_type": "post_reaction",
                "value": "2"
            },
            {
                "action_type": "link_click",
                "value": "2"
            }
        ],
        "date_start": "2025-03-30",
        "date_stop": "2025-03-30"
    },
    {
        "impressions": "3069",
        "account_id": "1213925972283556",
        "reach": "2115",
        "spend": "24.5",
        "adset_id": "120220302929240221",
        "adset_name": "05 | ADV+ | PROMO_01 | 0104",
        "ad_id": "120220302929300221",
        "ad_name": "AD09 | \"Fachada\" | 1303",
        "actions": [
            {
                "action_type": "page_engagement",
                "value": "9"
            },
            {
                "action_type": "post_engagement",
                "value": "9"
            },
            {
                "action_type": "post",
                "value": "1"
            },
            {
                "action_type": "post_reaction",
                "value": "4"
            },
            {
                "action_type": "link_click",
                "value": "4"
            }
        ],
        "date_start": "2025-03-30",
        "date_stop": "2025-03-30"
    },
    {
        "impressions": "1765",
        "account_id": "1213925972283556",
        "reach": "1271",
        "spend": "15.21",
        "adset_id": "120220302929240221",
        "adset_name": "05 | ADV+ | PROMO_01 | 0104",
        "ad_id": "120220302929310221",
        "ad_name": "AD08 | \"interno\" | 1602",
        "actions": [
            {
                "action_type": "onsite_conversion.total_messaging_connection",
                "value": "1"
            },
            {
                "action_type": "page_engagement",
                "value": "4"
            },
            {
                "action_type": "post_engagement",
                "value": "4"
            },
            {
                "action_type": "onsite_conversion.messaging_conversation_started_7d",
                "value": "1"
            },
            {
                "action_type": "link_click",
                "value": "4"
            }
        ],
        "date_start": "2025-03-30",
        "date_stop": "2025-03-30"
    },
    {
        "impressions": "1157",
        "account_id": "1213925972283556",
        "reach": "958",
        "spend": "13.77",
        "adset_id": "120220302929240221",
        "adset_name": "05 | ADV+ | PROMO_01 | 0104",
        "ad_id": "120220302929320221",
        "ad_name": "AD05 | \"interno\" | 1801",
        "actions": [
            {
                "action_type": "onsite_conversion.total_messaging_connection",
                "value": "2"
            },
            {
                "action_type": "page_engagement",
                "value": "8"
            },
            {
                "action_type": "post_engagement",
                "value": "8"
            },
            {
                "action_type": "post_reaction",
                "value": "2"
            },
            {
                "action_type": "link_click",
                "value": "6"
            }
        ],
        "date_start": "2025-03-30",
        "date_stop": "2025-03-30"
    },
    {
        "impressions": "2473",
        "account_id": "1213925972283556",
        "reach": "1923",
        "spend": "19.78",
        "adset_id": "120220303014390221",
        "adset_name": "00 | MED VET | ADV+ | AUTO | 2003 — Cópia",
        "ad_id": "120220303014380221",
        "ad_name": "AD01 | \"Coordenador MedVet\" | 2003",
        "actions": [
            {
                "action_type": "page_engagement",
                "value": "311"
            },
            {
                "action_type": "post_engagement",
                "value": "311"
            },
            {
                "action_type": "onsite_conversion.post_save",
                "value": "1"
            },
            {
                "action_type": "video_view",
                "value": "297"
            },
            {
                "action_type": "post_reaction",
                "value": "8"
            },
            {
                "action_type": "link_click",
                "value": "5"
            }
        ],
        "date_start": "2025-03-30",
        "date_stop": "2025-03-30"
    },
    {
        "impressions": "1730",
        "account_id": "1213925972283556",
        "reach": "1418",
        "spend": "20.17",
        "adset_id": "120220303019180221",
        "adset_name": "01 | DIREITO | ADV+ | AUTO | 2003 — Cópia",
        "ad_id": "120220303019170221",
        "ad_name": "AD01 | \"Coordenadora Direito\" | 2003",
        "actions": [
            {
                "action_type": "onsite_conversion.total_messaging_connection",
                "value": "1"
            },
            {
                "action_type": "page_engagement",
                "value": "292"
            },
            {
                "action_type": "post_engagement",
                "value": "292"
            },
            {
                "action_type": "onsite_conversion.messaging_conversation_started_7d",
                "value": "1"
            },
            {
                "action_type": "video_view",
                "value": "273"
            },
            {
                "action_type": "post_reaction",
                "value": "11"
            },
            {
                "action_type": "link_click",
                "value": "8"
            }
        ],
        "date_start": "2025-03-30",
        "date_stop": "2025-03-30"
    },
    {
        "impressions": "2057",
        "account_id": "1213925972283556",
        "reach": "1777",
        "spend": "22.88",
        "adset_id": "120220303027510221",
        "adset_name": "02 | PSICOLOGIA | ADV+ | AUTO | 2003 — Cópia",
        "ad_id": "120220303027500221",
        "ad_name": "AD01 | \"Coordenadora Psicologia\" | 2003",
        "actions": [
            {
                "action_type": "page_engagement",
                "value": "429"
            },
            {
                "action_type": "post_engagement",
                "value": "428"
            },
            {
                "action_type": "comment",
                "value": "2"
            },
            {
                "action_type": "like",
                "value": "1"
            },
            {
                "action_type": "video_view",
                "value": "392"
            },
            {
                "action_type": "post_reaction",
                "value": "18"
            },
            {
                "action_type": "link_click",
                "value": "16"
            }
        ],
        "date_start": "2025-03-30",
        "date_stop": "2025-03-30"
    },
    {
        "impressions": "2303",
        "account_id": "1213925972283556",
        "reach": "1655",
        "spend": "21.13",
        "adset_id": "120220303039920221",
        "adset_name": "03 | ENFERMAGEM | ADV+ | AUTO | 2003 — Cópia",
        "ad_id": "120220303039910221",
        "ad_name": "AD01 | \"Coordenadora Enfermagem\" | 2003",
        "actions": [
            {
                "action_type": "onsite_conversion.total_messaging_connection",
                "value": "1"
            },
            {
                "action_type": "page_engagement",
                "value": "257"
            },
            {
                "action_type": "post_engagement",
                "value": "257"
            },
            {
                "action_type": "onsite_conversion.messaging_conversation_started_7d",
                "value": "1"
            },
            {
                "action_type": "video_view",
                "value": "236"
            },
            {
                "action_type": "post_reaction",
                "value": "9"
            },
            {
                "action_type": "link_click",
                "value": "12"
            }
        ],
        "date_start": "2025-03-30",
        "date_stop": "2025-03-30"
    },
    {
        "impressions": "1846",
        "account_id": "1213925972283556",
        "reach": "1416",
        "spend": "19.76",
        "adset_id": "120220303057420221",
        "adset_name": "04 | FISIO | ADV+ | AUTO | 2003 — Cópia",
        "ad_id": "120220303057450221",
        "ad_name": "AD01 | \"Coordenador Fisio\" | 2003",
        "actions": [
            {
                "action_type": "onsite_conversion.total_messaging_connection",
                "value": "1"
            },
            {
                "action_type": "page_engagement",
                "value": "277"
            },
            {
                "action_type": "post_engagement",
                "value": "277"
            },
            {
                "action_type": "video_view",
                "value": "260"
            },
            {
                "action_type": "post_reaction",
                "value": "3"
            },
            {
                "action_type": "link_click",
                "value": "14"
            }
        ],
        "date_start": "2025-03-30",
        "date_stop": "2025-03-30"
    },
    {
        "impressions": "1873",
        "account_id": "1213925972283556",
        "reach": "1452",
        "spend": "22.63",
        "adset_id": "120220303089210221",
        "adset_name": "05 | FARMACIA | ADV+ | AUTO | 2003 — Cópia",
        "ad_id": "120220303089200221",
        "ad_name": "AD01 | \"Coordenador Farmacia\" | 2003",
        "actions": [
            {
                "action_type": "onsite_conversion.total_messaging_connection",
                "value": "1"
            },
            {
                "action_type": "page_engagement",
                "value": "295"
            },
            {
                "action_type": "post_engagement",
                "value": "295"
            },
            {
                "action_type": "comment",
                "value": "1"
            },
            {
                "action_type": "post",
                "value": "1"
            },
            {
                "action_type": "video_view",
                "value": "278"
            },
            {
                "action_type": "post_reaction",
                "value": "6"
            },
            {
                "action_type": "link_click",
                "value": "9"
            }
        ],
        "date_start": "2025-03-30",
        "date_stop": "2025-03-30"
    },
    {
        "impressions": "954",
        "account_id": "1213925972283556",
        "reach": "658",
        "spend": "8.07",
        "adset_id": "120220410993010221",
        "adset_name": "06 | Aberto | 18-44 | Transferências | 2403",
        "ad_id": "120220411031280221",
        "ad_name": "AD13 | \"Transferencias\" | 2403",
        "actions": [
            {
                "action_type": "onsite_conversion.total_messaging_connection",
                "value": "2"
            },
            {
                "action_type": "page_engagement",
                "value": "12"
            },
            {
                "action_type": "post_engagement",
                "value": "12"
            },
            {
                "action_type": "onsite_conversion.post_save",
                "value": "1"
            },
            {
                "action_type": "onsite_conversion.messaging_first_reply",
                "value": "1"
            },
            {
                "action_type": "post",
                "value": "1"
            },
            {
                "action_type": "onsite_conversion.messaging_conversation_started_7d",
                "value": "1"
            },
            {
                "action_type": "post_reaction",
                "value": "1"
            },
            {
                "action_type": "link_click",
                "value": "9"
            }
        ],
        "date_start": "2025-03-30",
        "date_stop": "2025-03-30"
    }
]