[
    {
        "impressions": "8",
        "account_id": "2442763915849323",
        "reach": "5",
        "spend": "0.05",
        "adset_id": "120213718014750249",
        "adset_name": "[MSGS] [26/11] — [QG] [ABERTO-18/65] [VÁRIAS CIDADES]",
        "ad_id": "120213718014760249",
        "ad_name": "[AD] [DIREITO]-[26/11]",
        "date_start": "2025-03-27",
        "date_stop": "2025-03-27"
    },
    {
        "impressions": "416",
        "account_id": "2442763915849323",
        "reach": "312",
        "spend": "7.73",
        "adset_id": "120213718014750249",
        "adset_name": "[MSGS] [26/11] — [QG] [ABERTO-18/65] [VÁRIAS CIDADES]",
        "ad_id": "120213718014770249",
        "ad_name": "[AD] [PSICOLOGIA]-[26/11]",
        "actions": [
            {
                "action_type": "onsite_conversion.total_messaging_connection",
                "value": "1"
            },
            {
                "action_type": "page_engagement",
                "value": "3"
            },
            {
                "action_type": "post_engagement",
                "value": "3"
            },
            {
                "action_type": "onsite_conversion.post_save",
                "value": "1"
            },
            {
                "action_type": "onsite_conversion.messaging_user_depth_2_message_send",
                "value": "1"
            },
            {
                "action_type": "onsite_conversion.messaging_conversation_started_7d",
                "value": "2"
            },
            {
                "action_type": "link_click",
                "value": "2"
            }
        ],
        "date_start": "2025-03-27",
        "date_stop": "2025-03-27"
    },
    {
        "impressions": "89",
        "account_id": "2442763915849323",
        "reach": "64",
        "spend": "1.31",
        "adset_id": "120213481903790249",
        "adset_name": "[REMARKETING] [17/11] [DIREITO] [MIX MORNO]",
        "ad_id": "120213719019230249",
        "ad_name": "[AD] [ODONTO-PORCENTAGEM] [03/03]",
        "actions": [
            {
                "action_type": "page_engagement",
                "value": "1"
            },
            {
                "action_type": "post_engagement",
                "value": "1"
            },
            {
                "action_type": "link_click",
                "value": "1"
            }
        ],
        "date_start": "2025-03-27",
        "date_stop": "2025-03-27"
    },
    {
        "impressions": "80",
        "account_id": "2442763915849323",
        "reach": "69",
        "spend": "1.18",
        "adset_id": "120213481806010249",
        "adset_name": "[REMARKETING] [17/11]  [MIX MORNO] [PSICOLOGIA]",
        "ad_id": "120214278603090249",
        "ad_name": "[AD] [FISIOTERAPIA] [22/02]",
        "actions": [
            {
                "action_type": "page_engagement",
                "value": "1"
            },
            {
                "action_type": "post_engagement",
                "value": "1"
            },
            {
                "action_type": "link_click",
                "value": "1"
            }
        ],
        "date_start": "2025-03-27",
        "date_stop": "2025-03-27"
    },
    {
        "impressions": "450",
        "account_id": "2442763915849323",
        "reach": "347",
        "spend": "5.57",
        "adset_id": "120214770116620249",
        "adset_name": "[07/01] [PALMAS + CIDADES] [18/65] [INTERESSES]",
        "ad_id": "120214770116790249",
        "ad_name": "[AD 1] [VIDEO MARA NOGUEIRA] [07/01]",
        "actions": [
            {
                "action_type": "page_engagement",
                "value": "59"
            },
            {
                "action_type": "post_engagement",
                "value": "59"
            },
            {
                "action_type": "onsite_conversion.post_save",
                "value": "1"
            },
            {
                "action_type": "video_view",
                "value": "57"
            },
            {
                "action_type": "link_click",
                "value": "1"
            }
        ],
        "date_start": "2025-03-27",
        "date_stop": "2025-03-27"
    },
    {
        "impressions": "341",
        "account_id": "2442763915849323",
        "reach": "334",
        "spend": "1.26",
        "adset_id": "120211715550170249",
        "adset_name": "[18-45/INTERESSES] [PALMAS] [EXCLUSÃO DE PUB]",
        "ad_id": "120214953004850249",
        "ad_name": "[AD] [DIRETOR PEDRO] — [15/01]",
        "actions": [
            {
                "action_type": "page_engagement",
                "value": "52"
            },
            {
                "action_type": "post_engagement",
                "value": "52"
            },
            {
                "action_type": "video_view",
                "value": "48"
            },
            {
                "action_type": "link_click",
                "value": "4"
            }
        ],
        "date_start": "2025-03-27",
        "date_stop": "2025-03-27"
    },
    {
        "impressions": "155",
        "account_id": "2442763915849323",
        "reach": "87",
        "spend": "1.52",
        "adset_id": "120214770116620249",
        "adset_name": "[07/01] [PALMAS + CIDADES] [18/65] [INTERESSES]",
        "ad_id": "120216692380460249",
        "ad_name": "[AD 3] [IMG-MED VET] [17/02]",
        "date_start": "2025-03-27",
        "date_stop": "2025-03-27"
    },
    {
        "impressions": "17",
        "account_id": "2442763915849323",
        "reach": "15",
        "spend": "0.29",
        "adset_id": "120213718014750249",
        "adset_name": "[MSGS] [26/11] — [QG] [ABERTO-18/65] [VÁRIAS CIDADES]",
        "ad_id": "120217874749890249",
        "ad_name": "[AD] [OFERTA-MARÇO]-[28/02]",
        "date_start": "2025-03-27",
        "date_stop": "2025-03-27"
    },
    {
        "impressions": "1573",
        "account_id": "2442763915849323",
        "reach": "1440",
        "spend": "4.58",
        "adset_id": "120211715550170249",
        "adset_name": "[18-45/INTERESSES] [PALMAS] [EXCLUSÃO DE PUB]",
        "ad_id": "120217987123150249",
        "ad_name": "[AD] [BOAS VINDAS NOVA UNIDADE] — [03/03]",
        "actions": [
            {
                "action_type": "page_engagement",
                "value": "120"
            },
            {
                "action_type": "post_engagement",
                "value": "120"
            },
            {
                "action_type": "video_view",
                "value": "112"
            },
            {
                "action_type": "link_click",
                "value": "8"
            }
        ],
        "date_start": "2025-03-27",
        "date_stop": "2025-03-27"
    },
    {
        "impressions": "3053",
        "account_id": "2442763915849323",
        "reach": "2908",
        "spend": "5.83",
        "adset_id": "120213481524590249",
        "adset_name": "[ALC 1] [MIX MORNO]",
        "ad_id": "120217987580660249",
        "ad_name": "[AD] [PROMO MARÇO 1] [03/03]",
        "actions": [
            {
                "action_type": "onsite_conversion.total_messaging_connection",
                "value": "1"
            },
            {
                "action_type": "page_engagement",
                "value": "7"
            },
            {
                "action_type": "post_engagement",
                "value": "7"
            },
            {
                "action_type": "onsite_conversion.messaging_user_depth_2_message_send",
                "value": "1"
            },
            {
                "action_type": "onsite_conversion.messaging_first_reply",
                "value": "2"
            },
            {
                "action_type": "onsite_conversion.messaging_user_depth_3_message_send",
                "value": "1"
            },
            {
                "action_type": "onsite_conversion.messaging_conversation_started_7d",
                "value": "4"
            },
            {
                "action_type": "video_view",
                "value": "1"
            },
            {
                "action_type": "link_click",
                "value": "6"
            }
        ],
        "date_start": "2025-03-27",
        "date_stop": "2025-03-27"
    },
    {
        "impressions": "548",
        "account_id": "2442763915849323",
        "reach": "430",
        "spend": "7.34",
        "adset_id": "120214772785160249",
        "adset_name": "[18/65] [PALMAS+OUTRAS CIDADES] [INTERESSES]",
        "ad_id": "120217987864260249",
        "ad_name": "[AD] [VID-ODONTO] [03/03]",
        "actions": [
            {
                "action_type": "onsite_conversion.total_messaging_connection",
                "value": "2"
            },
            {
                "action_type": "page_engagement",
                "value": "74"
            },
            {
                "action_type": "post_engagement",
                "value": "74"
            },
            {
                "action_type": "onsite_conversion.messaging_user_depth_2_message_send",
                "value": "2"
            },
            {
                "action_type": "onsite_conversion.messaging_first_reply",
                "value": "1"
            },
            {
                "action_type": "onsite_conversion.messaging_user_depth_3_message_send",
                "value": "1"
            },
            {
                "action_type": "onsite_conversion.messaging_conversation_started_7d",
                "value": "2"
            },
            {
                "action_type": "video_view",
                "value": "71"
            },
            {
                "action_type": "link_click",
                "value": "3"
            }
        ],
        "date_start": "2025-03-27",
        "date_stop": "2025-03-27"
    },
    {
        "impressions": "588",
        "account_id": "2442763915849323",
        "reach": "453",
        "spend": "7.95",
        "adset_id": "120213481657720249",
        "adset_name": "[REMARKETING] [17/11] [EAD] [MIX MORNO]",
        "ad_id": "120217988248020249",
        "ad_name": "[AD] [NOVOS CARDS-MARÇO] [03/03]",
        "actions": [
            {
                "action_type": "onsite_conversion.total_messaging_connection",
                "value": "2"
            },
            {
                "action_type": "page_engagement",
                "value": "2"
            },
            {
                "action_type": "post_engagement",
                "value": "2"
            },
            {
                "action_type": "onsite_conversion.messaging_user_depth_2_message_send",
                "value": "1"
            },
            {
                "action_type": "onsite_conversion.messaging_first_reply",
                "value": "2"
            },
            {
                "action_type": "onsite_conversion.messaging_user_depth_3_message_send",
                "value": "2"
            },
            {
                "action_type": "onsite_conversion.messaging_conversation_started_7d",
                "value": "2"
            },
            {
                "action_type": "post_reaction",
                "value": "1"
            },
            {
                "action_type": "link_click",
                "value": "1"
            }
        ],
        "date_start": "2025-03-27",
        "date_stop": "2025-03-27"
    },
    {
        "impressions": "127",
        "account_id": "2442763915849323",
        "reach": "96",
        "spend": "3.61",
        "adset_id": "120213481806010249",
        "adset_name": "[REMARKETING] [17/11]  [MIX MORNO] [PSICOLOGIA]",
        "ad_id": "120218562022880249",
        "ad_name": "[AD] [PROFESSORA - FISIOTERAPIA] [12/03]",
        "actions": [
            {
                "action_type": "page_engagement",
                "value": "11"
            },
            {
                "action_type": "post_engagement",
                "value": "11"
            },
            {
                "action_type": "video_view",
                "value": "11"
            }
        ],
        "date_start": "2025-03-27",
        "date_stop": "2025-03-27"
    },
    {
        "impressions": "573",
        "account_id": "2442763915849323",
        "reach": "478",
        "spend": "7.31",
        "adset_id": "120214770983590249",
        "adset_name": "[07/01] [PALMAS + CIDADES] [18/65] [INTERESSES] — Cópia",
        "ad_id": "120218562735150249",
        "ad_name": "[AD] [PROFESSORA - FISIOTERAPIA] [12/03] — Cópia",
        "actions": [
            {
                "action_type": "onsite_conversion.total_messaging_connection",
                "value": "1"
            },
            {
                "action_type": "page_engagement",
                "value": "68"
            },
            {
                "action_type": "post_engagement",
                "value": "68"
            },
            {
                "action_type": "onsite_conversion.messaging_user_depth_2_message_send",
                "value": "1"
            },
            {
                "action_type": "onsite_conversion.messaging_first_reply",
                "value": "1"
            },
            {
                "action_type": "onsite_conversion.messaging_user_depth_3_message_send",
                "value": "1"
            },
            {
                "action_type": "onsite_conversion.messaging_conversation_started_7d",
                "value": "1"
            },
            {
                "action_type": "video_view",
                "value": "64"
            },
            {
                "action_type": "post_reaction",
                "value": "2"
            },
            {
                "action_type": "link_click",
                "value": "2"
            }
        ],
        "date_start": "2025-03-27",
        "date_stop": "2025-03-27"
    },
    {
        "impressions": "91",
        "account_id": "2442763915849323",
        "reach": "80",
        "spend": "2.6",
        "adset_id": "120214484528040249",
        "adset_name": "[EAD] [VÁRIAS CIDADES] [ABERTO] [18/65]",
        "ad_id": "120218819183930249",
        "ad_name": "[AD] [NUTRIÇÃO-EAD] [17/03]",
        "date_start": "2025-03-27",
        "date_stop": "2025-03-27"
    },
    {
        "impressions": "11",
        "account_id": "2442763915849323",
        "reach": "9",
        "spend": "0.09",
        "adset_id": "120214484528040249",
        "adset_name": "[EAD] [VÁRIAS CIDADES] [ABERTO] [18/65]",
        "ad_id": "120218819518530249",
        "ad_name": "[AD] [FISIOTERAPIA] [17/03]",
        "date_start": "2025-03-27",
        "date_stop": "2025-03-27"
    },
    {
        "impressions": "647",
        "account_id": "2442763915849323",
        "reach": "508",
        "spend": "7.36",
        "adset_id": "120214484528040249",
        "adset_name": "[EAD] [VÁRIAS CIDADES] [ABERTO] [18/65]",
        "ad_id": "120219134735340249",
        "ad_name": "[AD] [BIOMEDICINA-EAD] [24/03]",
        "actions": [
            {
                "action_type": "page_engagement",
                "value": "5"
            },
            {
                "action_type": "post_engagement",
                "value": "5"
            },
            {
                "action_type": "video_view",
                "value": "1"
            },
            {
                "action_type": "post_reaction",
                "value": "2"
            },
            {
                "action_type": "link_click",
                "value": "2"
            }
        ],
        "date_start": "2025-03-27",
        "date_stop": "2025-03-27"
    }
]