[
    {
        "impressions": "289",
        "account_id": "2598162083676218",
        "reach": "238",
        "spend": "9.86",
        "adset_id": "120216443607390182",
        "adset_name": "[TRÁFEGO] [MSG] EAD - 02",
        "ad_id": "120218169656200182",
        "ad_name": "[AD] - HOMEM",
        "actions": [
            {
                "action_type": "onsite_conversion.total_messaging_connection",
                "value": "2"
            },
            {
                "action_type": "page_engagement",
                "value": "2"
            },
            {
                "action_type": "post_engagement",
                "value": "2"
            },
            {
                "action_type": "onsite_conversion.messaging_first_reply",
                "value": "1"
            },
            {
                "action_type": "onsite_conversion.messaging_conversation_started_7d",
                "value": "2"
            },
            {
                "action_type": "link_click",
                "value": "2"
            }
        ],
        "date_start": "2025-04-06",
        "date_stop": "2025-04-06"
    },
    {
        "impressions": "1365",
        "account_id": "2598162083676218",
        "reach": "1076",
        "spend": "35.41",
        "adset_id": "120216443607390182",
        "adset_name": "[TRÁFEGO] [MSG] EAD - 02",
        "ad_id": "120218169656210182",
        "ad_name": "[AD] - MULHER",
        "actions": [
            {
                "action_type": "onsite_conversion.total_messaging_connection",
                "value": "1"
            },
            {
                "action_type": "page_engagement",
                "value": "4"
            },
            {
                "action_type": "post_engagement",
                "value": "4"
            },
            {
                "action_type": "onsite_conversion.messaging_first_reply",
                "value": "1"
            },
            {
                "action_type": "onsite_conversion.messaging_conversation_started_7d",
                "value": "1"
            },
            {
                "action_type": "post_reaction",
                "value": "1"
            },
            {
                "action_type": "link_click",
                "value": "3"
            }
        ],
        "date_start": "2025-04-06",
        "date_stop": "2025-04-06"
    }
]