[
    {
        "impressions": "0",
        "account_id": "300036158051894",
        "reach": "0",
        "spend": "0",
        "adset_id": "120218216965720443",
        "adset_name": "Parnaiba+40km adv+",
        "ad_id": "120218992259620443",
        "ad_name": "mês do consumidor — 2",
        "actions": [
            {
                "action_type": "onsite_conversion.total_messaging_connection",
                "value": "1"
            },
            {
                "action_type": "onsite_conversion.messaging_user_depth_2_message_send",
                "value": "1"
            },
            {
                "action_type": "onsite_conversion.messaging_user_depth_3_message_send",
                "value": "1"
            }
        ],
        "date_start": "2025-04-03",
        "date_stop": "2025-04-03"
    },
    {
        "impressions": "3381",
        "account_id": "300036158051894",
        "reach": "2270",
        "spend": "36.31",
        "adset_id": "120218992319170443",
        "adset_name": "Parnaiba+40km adv+",
        "ad_id": "120218992319200443",
        "ad_name": "Transferencia",
        "actions": [
            {
                "action_type": "onsite_conversion.total_messaging_connection",
                "value": "4"
            },
            {
                "action_type": "page_engagement",
                "value": "19"
            },
            {
                "action_type": "post_engagement",
                "value": "19"
            },
            {
                "action_type": "onsite_conversion.messaging_user_depth_2_message_send",
                "value": "2"
            },
            {
                "action_type": "onsite_conversion.messaging_first_reply",
                "value": "3"
            },
            {
                "action_type": "onsite_conversion.messaging_user_depth_3_message_send",
                "value": "2"
            },
            {
                "action_type": "onsite_conversion.messaging_conversation_started_7d",
                "value": "4"
            },
            {
                "action_type": "video_view",
                "value": "3"
            },
            {
                "action_type": "post_reaction",
                "value": "2"
            },
            {
                "action_type": "link_click",
                "value": "14"
            }
        ],
        "date_start": "2025-04-03",
        "date_stop": "2025-04-03"
    },
    {
        "impressions": "56308",
        "account_id": "300036158051894",
        "reach": "35813",
        "spend": "439.16",
        "adset_id": "120217250256650443",
        "adset_name": "Parnaiba+40km adv+",
        "ad_id": "120220324438920443",
        "ad_name": "Promo 3",
        "actions": [
            {
                "action_type": "onsite_conversion.total_messaging_connection",
                "value": "8"
            },
            {
                "action_type": "page_engagement",
                "value": "229"
            },
            {
                "action_type": "post_engagement",
                "value": "229"
            },
            {
                "action_type": "onsite_conversion.post_save",
                "value": "1"
            },
            {
                "action_type": "onsite_conversion.messaging_user_depth_2_message_send",
                "value": "4"
            },
            {
                "action_type": "onsite_conversion.messaging_first_reply",
                "value": "7"
            },
            {
                "action_type": "onsite_conversion.messaging_user_depth_3_message_send",
                "value": "2"
            },
            {
                "action_type": "onsite_conversion.messaging_conversation_started_7d",
                "value": "9"
            },
            {
                "action_type": "video_view",
                "value": "34"
            },
            {
                "action_type": "post_reaction",
                "value": "38"
            },
            {
                "action_type": "link_click",
                "value": "156"
            }
        ],
        "date_start": "2025-04-03",
        "date_stop": "2025-04-03"
    }
]