[
    {
        "impressions": "10973",
        "account_id": "506161170713365",
        "reach": "7797",
        "spend": "120.81",
        "adset_id": "120218062881150078",
        "adset_name": "MêsDoConsumidor_01_31_03",
        "ad_id": "120218062881140078",
        "ad_name": "Criativo_01",
        "actions": [
            {
                "action_type": "onsite_conversion.total_messaging_connection",
                "value": "5"
            },
            {
                "action_type": "onsite_conversion.lead",
                "value": "2"
            },
            {
                "action_type": "page_engagement",
                "value": "53"
            },
            {
                "action_type": "post_engagement",
                "value": "53"
            },
            {
                "action_type": "onsite_conversion.messaging_user_depth_2_message_send",
                "value": "1"
            },
            {
                "action_type": "onsite_conversion.messaging_first_reply",
                "value": "6"
            },
            {
                "action_type": "onsite_web_lead",
                "value": "2"
            },
            {
                "action_type": "lead",
                "value": "5"
            },
            {
                "action_type": "onsite_conversion.messaging_user_depth_3_message_send",
                "value": "1"
            },
            {
                "action_type": "onsite_conversion.messaging_conversation_started_7d",
                "value": "7"
            },
            {
                "action_type": "onsite_conversion.lead_grouped",
                "value": "5"
            },
            {
                "action_type": "post_reaction",
                "value": "4"
            },
            {
                "action_type": "link_click",
                "value": "49"
            }
        ],
        "date_start": "2025-03-07",
        "date_stop": "2025-03-07"
    }
]