[
    {
        "impressions": "4801",
        "account_id": "5434306676675337",
        "reach": "3418",
        "spend": "25.19",
        "adset_id": "120216949224900434",
        "adset_name": "[FORMS][PATOS E REGIÃO][MARÇO] - EAD - NOVAS PEÇAS",
        "ad_id": "120216949224920434",
        "ad_name": "[AD][MULHER] - 01",
        "actions": [
            {
                "action_type": "page_engagement",
                "value": "19"
            },
            {
                "action_type": "post_engagement",
                "value": "19"
            },
            {
                "action_type": "lead",
                "value": "3"
            },
            {
                "action_type": "onsite_conversion.messaging_conversation_started_7d",
                "value": "1"
            },
            {
                "action_type": "onsite_conversion.lead_grouped",
                "value": "3"
            },
            {
                "action_type": "post_reaction",
                "value": "1"
            },
            {
                "action_type": "link_click",
                "value": "18"
            }
        ],
        "date_start": "2025-04-12",
        "date_stop": "2025-04-12"
    },
    {
        "impressions": "634",
        "account_id": "5434306676675337",
        "reach": "521",
        "spend": "3.09",
        "adset_id": "120216949224900434",
        "adset_name": "[FORMS][PATOS E REGIÃO][MARÇO] - EAD - NOVAS PEÇAS",
        "ad_id": "120216949880050434",
        "ad_name": "[AD][HOMEM] - 02",
        "actions": [
            {
                "action_type": "page_engagement",
                "value": "3"
            },
            {
                "action_type": "post_engagement",
                "value": "3"
            },
            {
                "action_type": "onsite_conversion.messaging_first_reply",
                "value": "1"
            },
            {
                "action_type": "lead",
                "value": "1"
            },
            {
                "action_type": "onsite_conversion.messaging_conversation_started_7d",
                "value": "1"
            },
            {
                "action_type": "onsite_conversion.lead_grouped",
                "value": "1"
            },
            {
                "action_type": "link_click",
                "value": "3"
            }
        ],
        "date_start": "2025-04-12",
        "date_stop": "2025-04-12"
    }
]